Metadata-Version: 2.1
Name: person-extractor
Version: 4.0.0
Summary: Extract people from text
Home-page: https://github.com/Mak4Lab/person-extractor
Author: Daniel J. Dufour, Victoria D. Mak
Author-email: daniel@mak4lab.com, victoria@mak4lab.com
License: UNKNOWN
Download-URL: https://github.com/Mak4Lab/person-extractor/tarball/download
Keywords: entity extraction,person
Platform: UNKNOWN
Classifier: Development Status :: 3 - Alpha
Classifier: Programming Language :: Python :: 3
Classifier: License :: CC0 1.0 Universal (CC0 1.0) Public Domain Dedication
Classifier: Operating System :: OS Independent
